lonny_common_pg/__init__.py
lonny_common_pg/connection.py
lonny_common_pg/logger.py
lonny_common_pg-0.1.0.dist-info/LICENSE
lonny_common_pg-0.1.0.dist-info/WHEEL
lonny_common_pg-0.1.0.dist-info/METADATA
lonny_common_pg-0.1.0.dist-info/RECORD
