Metadata-Version: 2.1
Name: lonny-common-pg
Version: 0.1.0
Summary: A quality-of-life wrapper for the psycopg2 connection object.
Home-page: https://lonny.io
Author: tlonny
Author-email: t@lonny.io
Requires-Python: >=3.8,<4.0
Classifier: Programming Language :: Python :: 3
Classifier: Programming Language :: Python :: 3.8
Requires-Dist: lonny_common_sql (>=0.1.0,<0.2.0)
Requires-Dist: psycopg2-binary (>=2.8.5,<3.0.0)
Project-URL: Repository, https://gitlab.com/lonny-common/pg
